geovisio/__init__.py
geovisio/config_app.py
geovisio/db_migrations.py
geovisio/errors.py
geovisio/admin_cli/__init__.py
geovisio/admin_cli/cleanup.py
geovisio/admin_cli/db.py
geovisio/admin_cli/default_account_tokens.py
geovisio/admin_cli/reorder_sequences.py
geovisio/admin_cli/sequence_heading.py
geovisio/admin_cli/user.py
geovisio/templates/main.html
geovisio/templates/viewer.html
geovisio/translations/messages.pot
geovisio/translations/ar/LC_MESSAGES/messages.mo
geovisio/translations/ar/LC_MESSAGES/messages.po
geovisio/translations/be/LC_MESSAGES/messages.mo
geovisio/translations/be/LC_MESSAGES/messages.po
geovisio/translations/br/LC_MESSAGES/messages.mo
geovisio/translations/br/LC_MESSAGES/messages.po
geovisio/translations/da/LC_MESSAGES/messages.mo
geovisio/translations/da/LC_MESSAGES/messages.po
geovisio/translations/de/LC_MESSAGES/messages.mo
geovisio/translations/de/LC_MESSAGES/messages.po
geovisio/translations/el/LC_MESSAGES/messages.mo
geovisio/translations/el/LC_MESSAGES/messages.po
geovisio/translations/en/LC_MESSAGES/messages.mo
geovisio/translations/en/LC_MESSAGES/messages.po
geovisio/translations/eo/LC_MESSAGES/messages.mo
geovisio/translations/eo/LC_MESSAGES/messages.po
geovisio/translations/es/LC_MESSAGES/messages.mo
geovisio/translations/es/LC_MESSAGES/messages.po
geovisio/translations/fi/LC_MESSAGES/messages.mo
geovisio/translations/fi/LC_MESSAGES/messages.po
geovisio/translations/fr/LC_MESSAGES/messages.mo
geovisio/translations/fr/LC_MESSAGES/messages.po
geovisio/translations/hu/LC_MESSAGES/messages.mo
geovisio/translations/hu/LC_MESSAGES/messages.po
geovisio/translations/it/LC_MESSAGES/messages.mo
geovisio/translations/it/LC_MESSAGES/messages.po
geovisio/translations/ja/LC_MESSAGES/messages.mo
geovisio/translations/ja/LC_MESSAGES/messages.po
geovisio/translations/ko/LC_MESSAGES/messages.mo
geovisio/translations/ko/LC_MESSAGES/messages.po
geovisio/translations/nl/LC_MESSAGES/messages.mo
geovisio/translations/nl/LC_MESSAGES/messages.po
geovisio-2.11.0.dist-info/licenses/LICENSE
geovisio-2.11.0.dist-info/WHEEL
geovisio-2.11.0.dist-info/METADATA
geovisio-2.11.0.dist-info/RECORD
