Metadata-Version: 2.4
Name: geovisio
Version: 2.11.0
Summary: GeoVisio API - Main
Author-email: Adrien PAVIE <panieravide@riseup.net>, Antoine Desbordes <antoine.desbordes@gmail.com>
Requires-Python: >=3.10
Classifier: License :: OSI Approved :: MIT License
License-File: LICENSE
Requires-Dist: Flask ~= 3.1
Requires-Dist: psycopg[pool] ~= 3.2
Requires-Dist: flasgger ~= 0.9.7
Requires-Dist: Pillow ~= 11.1
Requires-Dist: Flask-Cors ~= 6.0
Requires-Dist: fs ~= 2.4
Requires-Dist: fs-s3fs-forked ~= 1.1.4
Requires-Dist: flask-compress ~= 1.14
Requires-Dist: requests ~= 2.31
Requires-Dist: yoyo-migrations ~= 9.0
Requires-Dist: psycopg-binary ~= 3.2
Requires-Dist: python-dotenv ~= 1.1
Requires-Dist: authlib ~= 1.6
Requires-Dist: Flask-Executor ~= 1.0
Requires-Dist: geopic-tag-reader[write-exif] ~= 1.8.0
Requires-Dist: rfeed ~= 1.1.1
Requires-Dist: sentry-sdk[flask] ~= 2.24
Requires-Dist: pygeofilter[backend-native] ~= 0.3.1
Requires-Dist: python-dateutil ~= 2.9.0
Requires-Dist: tzdata ~= 2025.2
Requires-Dist: croniter ~= 6.0.0
Requires-Dist: pydantic ~= 2.12
Requires-Dist: pydantic-extra-types ~= 2.7
Requires-Dist: flask-babel ~= 4.0.0
Requires-Dist: geojson-pydantic ~= 2.0.0
Requires-Dist: email-validator ~= 2.2.0
Requires-Dist: multipart>=1.2.1
Requires-Dist: gunicorn ~= 23.0.0
Requires-Dist: flit ~= 3.9.0 ; extra == "build"
Requires-Dist: coverage ~= 7.9 ; extra == "dev"
Requires-Dist: protobuf ~= 5.26 ; extra == "dev"
Requires-Dist: mapbox-vector-tile ~= 2.1 ; extra == "dev"
Requires-Dist: pystac ~= 1.9 ; extra == "dev"
Requires-Dist: pytest ~= 8.4 ; extra == "dev"
Requires-Dist: pytest-datafiles ~= 3.0 ; extra == "dev"
Requires-Dist: pyexiv2 ~= 2.15 ; extra == "dev"
Requires-Dist: testcontainers ~= 4.10 ; extra == "dev"
Requires-Dist: requests-mock ~= 1.11 ; extra == "dev"
Requires-Dist: black ~= 25.1 ; extra == "dev"
Requires-Dist: pre-commit ~= 4.2 ; extra == "dev"
Requires-Dist: pyyaml ~= 6.0 ; extra == "dev"
Requires-Dist: openapi-spec-validator ~= 0.7 ; extra == "dev"
Requires-Dist: stac-api-validator ~= 0.6.4 ; extra == "dev"
Requires-Dist: mkdocs-material ~= 9.6.14 ; extra == "docs"
Requires-Dist: mkdocs-swagger-ui-tag ~= 0.7.1 ; extra == "docs"
Project-URL: Home, https://gitlab.com/panoramax/server/api
Project-URL: Source Code, https://gitlab.com/panoramax/server/api
Provides-Extra: build
Provides-Extra: dev
Provides-Extra: docs
